LICENSE
MANIFEST.in
README.md
setup.py
disnake_jishaku.egg-info/PKG-INFO
disnake_jishaku.egg-info/SOURCES.txt
disnake_jishaku.egg-info/dependency_links.txt
disnake_jishaku.egg-info/requires.txt
disnake_jishaku.egg-info/top_level.txt
jishaku/__init__.py
jishaku/__main__.py
jishaku/codeblocks.py
jishaku/cog.py
jishaku/exception_handling.py
jishaku/flags.py
jishaku/functools.py
jishaku/help_command.py
jishaku/hljs.py
jishaku/meta.py
jishaku/models.py
jishaku/modules.py
jishaku/paginators.py
jishaku/shell.py
jishaku/features/__init__.py
jishaku/features/baseclass.py
jishaku/features/filesystem.py
jishaku/features/guild.py
jishaku/features/invocation.py
jishaku/features/management.py
jishaku/features/python.py
jishaku/features/root_command.py
jishaku/features/shell.py
jishaku/features/voice.py
jishaku/features/youtube.py
jishaku/repl/__init__.py
jishaku/repl/compilation.py
jishaku/repl/disassembly.py
jishaku/repl/inspections.py
jishaku/repl/repl_builtins.py
jishaku/repl/scope.py
jishaku/repl/walkers.py
jishaku/shim/paginator_200.py
jishaku/shim/paginator_base.py
requirements/_.txt
requirements/procinfo.txt
requirements/test.txt
requirements/voice.txt