Metadata-Version: 2.1
Name: disnake-jishaku
Version: 2.6.1
Summary: A disnake extension including useful tools for bot development and debugging.
Home-page: https://github.com/Kraots/jishaku
Author: Kraots
License: MIT
Download-URL: https://github.com/Kraots/jishaku/archive/2.6.1.tar.gz
Project-URL: Code, https://github.com/Kraots/jishaku
Project-URL: Issue tracker, https://github.com/Kraots/jishaku/issues
Keywords: jishaku disnake disnake-jishaku discord cog repl extension
Platform: UNKNOWN
Classifier: Development Status :: 5 - Production/Stable
Classifier: Framework :: AsyncIO
Classifier: Intended Audience :: Developers
Classifier: License :: OSI Approved :: MIT License
Classifier: Natural Language :: English
Classifier: Operating System :: OS Independent
Classifier: Programming Language :: Python :: 3 :: Only
Classifier: Programming Language :: Python :: 3.8
Classifier: Programming Language :: Python :: 3.9
Classifier: Topic :: Communications :: Chat
Classifier: Topic :: Internet
Classifier: Topic :: Software Development :: Debuggers
Classifier: Topic :: Software Development :: Testing
Classifier: Topic :: Utilities
Requires-Python: >=3.8.0
Provides-Extra: docs
Provides-Extra: procinfo
Provides-Extra: publish
Provides-Extra: test
Provides-Extra: voice
